[{"id":"3fdac368-665b-4648-9e5d-1138edd51567","user_id":"813695ea-2a34-4c90-820f-3a11ade96f91","fingerprint":"fp_6z7ggb","device_info":{"os": "macOS 10.15.7", "screen": "1680x1050", "browser": "Chrome 144.0.0.0", "language": "uk-UA", "timezone": "Europe/Warsaw", "device_type": "Desktop"},"ip_address":"::1","blocked":true,"created_at":"2026-02-17T12:20:12.229591+00:00"}, 
 {"id":"7f2048ef-4fd3-4c96-aa4b-b0f7ff3ad5f5","user_id":"813695ea-2a34-4c90-820f-3a11ade96f91","fingerprint":"fp_6z7ggb","device_info":{"os": "macOS 10.15.7", "screen": "1680x1050", "browser": "Chrome 144.0.0.0", "language": "uk-UA", "timezone": "Europe/Warsaw", "device_type": "Desktop"},"ip_address":"::1","blocked":true,"created_at":"2026-02-17T12:20:27.647853+00:00"}, 
 {"id":"4efa60c8-9736-461c-8b14-5c11b79fb95e","user_id":"813695ea-2a34-4c90-820f-3a11ade96f91","fingerprint":"fp_5o6p6m","device_info":{"os": "macOS 10.15.7", "screen": "1680x1050", "browser": "Chrome 144.0.0.0", "language": "uk-UA", "timezone": "Europe/Warsaw", "device_type": "Desktop"},"ip_address":"::1","blocked":true,"created_at":"2026-02-17T12:20:52.572256+00:00"}]